<?xml version="1.0" encoding="utf-8"?>
    <TileMap version="1.0.0" tilemapservice="http://tms.osgeo.org/1.0.0">
      <Title>Schwarzplan</Title>
      <Abstract></Abstract>
      <SRS>EPSG:3857</SRS>
      <BoundingBox minx="14.30522229550299" miny="51.73538626510637" maxx="14.35858222343412" maxy="51.78209881565247"/>
      <Origin x="14.30522229550299" y="51.73538626510637"/>
      <TileFormat width="256" height="256" mime-type="image/png" extension="png"/>
      <TileSets profile="mercator">
        <TileSet href="12" units-per-pixel="38.21851413574219" order="12"/>
        <TileSet href="13" units-per-pixel="19.10925706787109" order="13"/>
        <TileSet href="14" units-per-pixel="9.55462853393555" order="14"/>
        <TileSet href="15" units-per-pixel="4.77731426696777" order="15"/>
        <TileSet href="16" units-per-pixel="2.38865713348389" order="16"/>
      </TileSets>
    </TileMap>
    